random_proxies/__init__.py
random_proxies/cache/__init__.py
random_proxies/cache/app.py
random_proxies/cache/main/__init__.py
random_proxies/cache/main/clean.py
random_proxies/cache/main/routine.py
random_proxies/cache/main/update.py
random_proxies/proxies/__init__.py
random_proxies/proxies/db.py
random_proxies/proxies/exception.py
random_proxies/proxies/log.py
random_proxies/proxies/proxy.py
random_proxies/proxies/proxy_health.py
random_proxies/proxies/settings.py
random_proxies/proxies/utils.py
random_proxies-0.0.2.dist-info/LICENSE.txt
random_proxies-0.0.2.dist-info/METADATA
random_proxies-0.0.2.dist-info/WHEEL
random_proxies-0.0.2.dist-info/top_level.txt
random_proxies-0.0.2.dist-info/RECORD
