Metadata-Version: 2.1
Name: random_proxies
Version: 0.0.2
Summary: Get a proxy server IP on the fly!
Home-page: https://github.com/2knal/random_proxies
Author: Kunal Sonawane
Author-email: kunal.sonawane@somaiya.edu
License: MIT
Platform: UNKNOWN
Classifier: License :: OSI Approved :: MIT License
Classifier: Programming Language :: Python :: 3
Classifier: Programming Language :: Python :: 3.7
